sqlalchemy_model_builder/__init__.py
sqlalchemy_model_builder/_models.py
sqlalchemy_model_builder/exceptions.py
sqlalchemy_model_builder/model_builder.py
sqlalchemy_model_builder/random_builder.py
sqlalchemy_model_builder-0.3.0.dist-info/METADATA
sqlalchemy_model_builder-0.3.0.dist-info/WHEEL
sqlalchemy_model_builder-0.3.0.dist-info/licenses/LICENSE
sqlalchemy_model_builder-0.3.0.dist-info/RECORD
