Metadata-Version: 2.1
Name: sqlalchemy-model-builder
Version: 0.3.0
Summary: SQLAlchemy Model Builder
Project-URL: Documentation, https://github.com/aminalaee/sqlalchemy-model-builder
Project-URL: Issues, https://github.com/aminalaee/sqlalchemy-model-builder/issues
Project-URL: Source, https://github.com/aminalaee/sqlalchemy-model-builder
Author-email: Amin Alaee <me@aminalaee.dev>
License-Expression: MIT
License-File: LICENSE
Keywords: sqlalchemy,testing
Classifier: Development Status :: 4 - Beta
Classifier: Environment :: Web Environment
Classifier: Intended Audience :: Developers
Classifier: Operating System :: OS Independent
Classifier: Programming Language :: Python
Classifier: Programming Language :: Python :: 3.7
Classifier: Programming Language :: Python :: 3.8
Classifier: Programming Language :: Python :: 3.9
Classifier: Programming Language :: Python :: 3.10
Classifier: Programming Language :: Python :: 3.11
Requires-Python: >=3.7
Requires-Dist: sqlalchemy>=1.4
